{
  "LAVADORA": 1,
  "SECADORA": 2,
  "LICUADORA": 3,
  "ASPIRADORA": 4,
  "TOSTADORA": 5,
  "FREIDORA": 6,
  "AFEITADORA": 7,
  "AMASADORA": 8,
  "LIJADORA": 9,
  "EMPACADORA": 10,
  "GRAPADORA": 11,
  "CALADORA": 12,
  "HIDROLIMPIADORA": 13,
  "INODORA": 14,
  "VITROCERAMICA": 15,
  "CONGELADORA": 16,
  "LAVARROPA": 17,
  "CENTRIFUGADORA": 18,
  "WHIRLPOOL": 19,
  "PELADORA": 20,
  "SOPLADORA": 21,
  "PLANCHADORA": 22,
  "RASURADORA": 23,
  "HIDROLAVADORA": 24,
  "FREGADORA": 25,
  "DESMOTADORA": 26,
  "REIDORA": 27,
  "ENGRAPADORA": 28,
  "DESFIBRADORA": 29,
  "ESMERILADORA": 30,
  "DESPALILLADORA": 31,
  "ROZADORA": 32,
  "RIZADORA": 33,
  "CLAVADORA": 34,
  "LAVAVAJILLAS": 35,
  "FREGADERO": 36,
  "SARTENES": 37,
  "INODOROS": 38,
  "SECADORAS": 39,
  "LAVAMANOS": 40,
  "LAVAPLATOS": 41,
  "LAVARROPAS": 42,
  "HORNILLAS": 43,
  "LAVACABEZAS": 44,
  "LAVAVAJILLA": 45,
  "FREGAO": 46,
  "VITROCERAMICAS": 47,
  "FREGADERA": 48,
  "LAVAPARABRISAS": 49,
  "LAVAOJOS": 50,
  "VITROCERAMICO": 51,
  "LAVANDERIA": 52,
  "CONSERJERIA": 53,
  "TINTORERIA": 54,
  "LAVANDERA": 55,
  "LAUNDRY": 56,
  "LAVANDERO": 57,
  "GUARDAESQUIS": 58,
  "SECADOR": 59,
  "RIZADOR": 60,
  "ALISADOR": 61,
  "PLANCHADOR": 62,
  "PLANCHA": 63,
  "PLANCHAR": 64,
  "PLANCHADA": 65,
  "PLANCHITA": 66,
  "PLANCHO": 67,
  "PLANCHABA": 68,
  "PLANCHAZO": 69,
  "PLANCHE": 70,
  "PLANCHARLO": 71,
  "PLANCHAN": 72,
  "CATAPLANA": 73,
  "CABRILLA": 74,
  "TENACILLA": 75,
  "PLANCHARLA": 76,
  "PLANCHUELA": 77,
  "PLANCHON": 78,
  "PLANCHES": 79,
  "PLANITA": 80,
  "PLANCHETA": 81,
  "CALENTADOR": 82,
  "TERMO": 83,
  "TERMOTANQUE": 84,
  "TERMOSIFON": 85,
  "ESTERILIZADOR": 86,
  "DESATASCADOR": 87,
  "TERMOSTATICO": 88,
  "AGUADOR": 89,
  "ESPESADOR": 90,
  "CALOPORTADOR": 91,
  "AUTOLIMPIANTE": 92,
  "PRECALENTADOR": 93,
  "OZONIZADOR": 94,
  "ESTUFA": 95,
  "ESTUFAS": 96,
  "CALEFON": 97,
  "ANAFE": 98,
  "CALEF": 99,
  "ANAFRES": 100,
  "ANAFES": 101,
  "CALEFONT": 102,
  "ANAFRE": 103,
  "LAVAR": 104,
  "LAVARSE": 105,
  "AFEITAR": 106,
  "FROTAR": 107,
  "BANAR": 108,
  "LAVAN": 109,
  "ENJUAGAR": 110,
  "LAVE": 111,
  "LAVARLO": 112,
  "LAVABA": 113,
  "LAVARLA": 114,
  "LAVARTE": 115,
  "LAVARLAS": 116,
  "LAVARLOS": 117,
  "LAVARME": 118,
  "LAVEN": 119,
  "LAVARLE": 120,
  "LAVATE": 121,
  "LAVARA": 122,
  "LAVANDINA": 123,
  "LAVAPIES": 124,
  "ENJUAGARLO": 125,
  "LAVESE": 126,
  "LAVARLES": 127,
  "EMBADURNAR": 128,
  "ENJUAGAN": 129,
  "ENJABONAR": 130,
  "LAVARAN": 131,
  "LAVALA": 132,
  "ENJUAGARLA": 133,
  "ENJUAGO": 134,
  "ENJUAGARTE": 135,
  "ENJUAGATE": 136,
  "LAVALIER": 137,
  "LAVALOS": 138,
  "VUIT": 139,
  "LAVANCO": 140,
  "LAVARAS": 141,
  "LAVAROS": 142,
  "JUAGAR": 143,
  "LAVASE": 144,
  "LAVASH": 145,
  "LAVARIA": 146,
  "LAVARE": 147,
  "MAQUINA": 148,
  "MAQUINITA": 149,
  "MAQUINILLA": 150,
  "MQUINA": 151,
  "CNC": 152,
  "EXTRUSORA": 153,
  "DREMEL": 154,
  "MACHINERY": 155,
  "MAQUINON": 156,
  "MEELKO": 157,
  "MOLEX": 158,
  "TALQUINA": 159,
  "MAQUINO": 160,
  "ELQUINA": 161,
  "EXTRUSION": 162,
  "TRIQUINA": 163,
  "VENTILADOR": 164,
  "RADIADOR": 165,
  "VIBRADOR": 166,
  "DIFUSOR": 167,
  "TERMOSTATO": 168,
  "ASPIRADOR": 169,
  "QUEMADOR": 170,
  "PULVERIZADOR": 171,
  "VENTILADO": 172,
  "DISIPADOR": 173,
  "LIMPIAPARABRISAS": 174,
  "VAPORIZADOR": 175,
  "CALEFACTOR": 176,
  "EVAPORADOR": 177,
  "TOSTADOR": 178,
  "ENFRIADOR": 179,
  "VELADOR": 180,
  "HUMIDIFICADOR": 181,
  "ROCIADOR": 182,
  "DESLIZADOR": 183,
  "FLEXO": 184,
  "VENTILA": 185,
  "BOILER": 186,
  "SOPLADOR": 187,
  "SPLITS": 188,
  "ROTADOR": 189,
  "NEBULIZADOR": 190,
  "DEFLECTOR": 191,
  "COOLER": 192,
  "TERMOPAR": 193,
  "DOBLADOR": 194,
  "DESHUMIDIFICADOR": 195,
  "INFLADOR": 196,
  "ZUMBADOR": 197,
  "AIREADOR": 198,
  "VENTILO": 199,
  "AISLADOR": 200,
  "AERODESLIZADOR": 201,
  "VENTEO": 202,
  "VENTILE": 203,
  "APILADOR": 204,
  "FUSOR": 205,
  "LADRADOR": 206,
  "VENTILAS": 207,
  "INCUBADOR": 208,
  "ELECTROVENTILADOR": 209,
  "VENTOLIN": 210,
  "VENTI": 211,
  "DAMPER": 212,
  "FRESADOR": 213,
  "ENGRASADOR": 214,
  "IRRADIADOR": 215,
  "RONCADOR": 216,
  "ESTATORREACTOR": 217,
  "ONDULADOR": 218,
  "LUBRICADOR": 219,
  "BESADOR": 220,
  "TERMOCICLADOR": 221,
  "EMPOTRADOR": 222,
  "POSTQUEMADOR": 223,
  "FANCOILS": 224,
  "PISADOR": 225,
  "PERCOLADOR": 226,
  "VENTILARA": 227,
  "MICROONDAS": 228,
  "MICROONDA": 229,
  "MICROHONDAS": 230,
  "MICRONDAS": 231,
  "MICROWAVE": 232,
  "VITROLA": 233,
  "CALEFACCION": 234,
  "CALEFACTORES": 235,
  "CLIMALIT": 236,
  "AEROTERMIA": 237,
  "CALEFACCIONES": 238,
  "CALEFACCIONAR": 239,
  "CALEFACCIONADOS": 240,
  "CALEFACTORAS": 241,
  "CALEFACTABLE": 242,
  "CALEFACTORA": 243,
  "CALEFACION": 244,
  "CALEFACCIONADA": 245,
  "CALEFACTADA": 246,
  "CALEFACCI": 247,
  "CALEFACCIN": 248,
  "CAFETERA": 249,
  "MINIBAR": 250,
  "TETERA": 251,
  "CAFETERO": 252,
  "NESPRESSO": 253,
  "MOULINEX": 254,
  "PRESSO": 255,
  "CAETERA": 256,
  "MAGEFESA": 257,
  "CETERA": 258,
  "LAVADO": 259,
  "BLANQUEO": 260,
  "LAVADOR": 261,
  "PRELAVADO": 262,
  "AUTOLAVADO": 263,
  "ANTILAVADO": 264,
  "LAVANTE": 265,
  "LIMPIA": 266,
  "LAVADA": 267,
  "LIMPIADA": 268,
  "DESINFECTA": 269,
  "AIREADA": 270,
  "ASEADA": 271,
  "LIMPITA": 272,
  "LIMPIANDOLA": 273,
  "LIMPISIMA": 274,
  "LIMPIALO": 275,
  "LIMP": 276,
  "LIMPIALA": 277,
  "LIMPIATE": 278,
  "LIMPI": 279,
  "LIMPIAIS": 280,
  "LIMPIEZA": 281,
  "LIMPIEZAS": 282,
  "LIMPIADORA": 283,
  "LIMPIEN": 284,
  "LIMPIES": 285,
  "AUTOLIMPIEZA": 286,
  "LIMPEZA": 287,
  "DESODORIZA": 288,
  "DESINFECCION": 289,
  "LIMPIESA": 290,
  "LIMPERS": 291,
  "TRITURADORA": 292,
  "TRITURADOR": 293,
  "TRITURADO": 294,
  "TRITURADA": 295,
  "TRITURA": 296,
  "SBM": 297,
  "PULVERIZADORA": 298,
  "TRITURE": 299,
  "BIOTRITURADORA": 300,
  "TRITURO": 301,
  "MOBILECRUSHERCHINA": 302,
  "DETRITURADORA": 303,
  "TRITURABA": 304,
  "CHINATRITURADORA": 305,
  "PCL": 306,
  "ЭТУ": 307,
  "ELECTRODOMESTICOS": 308,
  "LAVADORAS": 309,
  "ELECTRODOMESTICO": 310,
  "FRIGORIFICOS": 311,
  "REFRIGERADORES": 312,
  "SECADORES": 313,
  "ELECTROLUX": 314,
  "ELECTRODOMSTICOS": 315,
  "MAQUINARIA": 316,
  "MAQUINARIAS": 317,
  "RETROEXCAVADORA": 318,
  "MAQUINAR": 319,
  "DESBROZADORA": 320,
  "MOTONIVELADORA": 321,
  "MAQUINAL": 322,
  "MECANIZA": 323,
  "MAQUINARIO": 324,
  "COQUINARIA": 325,
  "MAQUINADA": 326,
  "DESMALEZADORA": 327,
  "QUINARIA": 328,
  "MAQUINARA": 329,
  "LAVADERO": 330,
  "TECHADA": 331,
  "QUINCHO": 332,
  "LAVADEROS": 333,
  "TENDEDERO": 334,
  "ASERRADERO": 335,
  "ABREVADERO": 336,
  "BACHA": 337,
  "LAVATORIO": 338,
  "TINACO": 339,
  "POSH": 340,
  "MEADERO": 341,
  "ZOTEHUELA": 342,
  "CALETRE": 343,
  "TOILETE": 344,
  "CAGADERO": 345,
  "LAVALLE": 346,
  "BASCULA": 347,
  "QUINA": 348,
  "VIRUTA": 349,
  "HILADORA": 350,
  "PUQUINA": 351,
  "TURBOMAQUINA": 352,
  "CALIENTE": 353,
  "VENTE": 354,
  "CALENTADA": 355,
  "ENFRIADA": 356,
  "GRASIENTO": 357,
  "CALIENTO": 358,
  "RECALENTADA": 359,
  "ENFRIADORA": 360,
  "SOBRECALIENTE": 361,
  "CONGELANTE": 362,
  "DESCONGELADA": 363,
  "RECALIENTE": 364,
  "CALENTO": 365,
  "PRECALENTADA": 366,
  "ESPESAN": 367,
  "CALENTORRAS": 368,
  "CALENTE": 369,
  "CALENTADORA": 370,
  "PASTEURIZADORA": 371,
  "CHANCADORA": 372,
  "CHANCADO": 373,
  "PICADORA": 374,
  "AMOLADORA": 375,
  "CHANCADOR": 376,
  "FRESADORA": 377,
  "ZARANDA": 378,
  "ZENITH": 379,
  "VIBRADORA": 380,
  "CRUSHER": 381,
  "VSI": 382,
  "MOLEDORA": 383,
  "MACHACADORA": 384,
  "QUEBRADORA": 385,
  "CONICA": 386,
  "TUNELADORA": 387,
  "DOBLADORA": 388,
  "MANDBULA": 389,
  "CHANCAR": 390,
  "CHANCADA": 391,
  "CHANCACA": 392,
  "CHANCAS": 393,
  "CHANCA": 394,
  "ASTILLADORA": 395,
  "TRILLADORA": 396,
  "JAW": 397,
  "CRIBADORA": 398,
  "PEW": 399,
  "ENSACADORA": 400,
  "PELETIZADORA": 401,
  "CHANCAPIEDRA": 402,
  "FACO": 403,
  "KEEL": 404,
  "INGLETADORA": 405,
  "KUE": 406,
  "HAZEMAG": 407,
  "CRUSHERS": 408,
  "HILTI": 409,
  "AFILADORA": 410,
  "CHANCAY": 411,
  "SVEDALA": 412,
  "DUCHA": 413,
  "REGADERA": 414,
  "BIDET": 415,
  "DUCHO": 416,
  "DUCHARTE": 417,
  "DUCHAR": 418,
  "DUCHITA": 419,
  "DUCHE": 420,
  "POCETA": 421,
  "TELEDUCHA": 422,
  "COCINA": 423,
  "ALACENA": 424,
  "CUBERTERIA": 425,
  "COCINETA": 426,
  "COCINITA": 427,
  "CUCINA": 428,
  "COCINILLA": 429,
  "COCIN": 430,
  "PUTRESCINA": 431,
  "PSILOCINA": 432,
  "TOKONOMA": 433,
  "REFRIGERACION": 434,
  "REFRIGERANTE": 435,
  "LUBRICACION": 436,
  "REFRIGERADO": 437,
  "REFRIGERANTES": 438,
  "REFRIGERADA": 439,
  "CENTRIFUGAS": 440,
  "AUTOCLAVE": 441,
  "INTERCOOLER": 442,
  "REFRIGERADORA": 443,
  "CARBURACION": 444,
  "TERMOSTATICA": 445,
  "REFRIGERADORAS": 446,
  "REGASIFICADORA": 447,
  "DISPENSADORA": 448,
  "ENFRIADORAS": 449,
  "TERMOFUSION": 450,
  "REFRIGERAN": 451,
  "EVAPORATIVA": 452,
  "PRESURIZADORA": 453,
  "EVAPORADORA": 454,
  "REJILLA": 455,
  "HORQUILLA": 456,
  "BOQUILLA": 457,
  "ENCIMERA": 458,
  "VARILLA": 459,
  "CUBETA": 460,
  "QUILLA": 461,
  "PERCHA": 462,
  "ANILLA": 463,
  "MOLDURA": 464,
  "MASILLA": 465,
  "ESCOTILLA": 466,
  "LOSETA": 467,
  "PATILLA": 468,
  "CANILLA": 469,
  "REGLETA": 470,
  "ESCOBILLA": 471,
  "CANALETA": 472,
  "CAZOLETA": 473,
  "BAQUETA": 474,
  "CANALON": 475,
  "PIQUETA": 476,
  "CALOTA": 477,
  "CEJILLA": 478,
  "HORNILLA": 479,
  "RANURADA": 480,
  "CUBITERA": 481,
  "PAJILLA": 482,
  "BARQUILLA": 483,
  "RASQUETA": 484,
  "PELUSILLA": 485,
  "CELDILLA": 486,
  "PUSILLA": 487,
  "COLADERA": 488,
  "GUTAPERCHA": 489,
  "HORQUETA": 490,
  "HOJILLA": 491,
  "TIRILLA": 492,
  "TOLDILLA": 493,
  "RUEDECILLA": 494,
  "MANGUITA": 495,
  "MANGUETA": 496,
  "CAJILLA": 497,
  "COQUILLA": 498,
  "CABILLA": 499,
  "REMACHADORA": 500,
  "BARILLA": 501,
  "MARQUILLA": 502,
  "LINTERNILLA": 503,
  "BARQUETA": 504,
  "TIRADERA": 505,
  "BONILLA": 506,
  "CORCHERA": 507,
  "ATARJEAS": 508,
  "MOSTACILLA": 509,
  "TRAPISONDA": 510,
  "CHALADURA": 511,
  "LIMPIAR": 512,
  "LIMPIAN": 513,
  "BARRER": 514,
  "LIMPIE": 515,
  "LIMPIARLO": 516,
  "DESINFECTAR": 517,
  "ROCIAR": 518,
  "LIMPIO": 519,
  "FREGAR": 520,
  "ALISAR": 521,
  "LIMPIARLA": 522,
  "LIMPIABA": 523,
  "LIMPIARLOS": 524,
  "LIMPIARLAS": 525,
  "LIMPIARME": 526,
  "LIMPIARA": 527,
  "LIMPIARLE": 528,
  "LIMPIABOTAS": 529,
  "LIMPIARNOS": 530,
  "LIMPIARTE": 531,
  "HIGIENIZAR": 532,
  "LIMPIARAN": 533,
  "TRAPEAR": 534,
  "DESENGRASE": 535,
  "LIMPIAPIPAS": 536,
  "LIMPIARIA": 537,
  "LIMPIARLES": 538,
  "LIMPIARE": 539,
  "DESINFECTE": 540,
  "LIMPIAD": 541,
  "DESODORIZAR": 542,
  "DIMINUIR": 543,
  "DESINFECTARLAS": 544,
  "LIMPIARAS": 545,
  "IMPRESORA": 546,
  "OFFSET": 547,
  "COPIADORA": 548,
  "FOTOCOPIADORA": 549,
  "SCANNER": 550,
  "ESCANER": 551,
  "PLOTTER": 552,
  "SCANNERS": 553,
  "TROQUELADORA": 554,
  "SCANER": 555,
  "IMPRESSION": 556,
  "IMPRESS": 557,
  "IMPRESSA": 558,
  "IMPRESSICOLLIS": 559,
  "RIBBONS": 560,
  "OFFSETS": 561,
  "IMPRESSED": 562,
  "NEVERA": 563,
  "HELADERA": 564,
  "FREEZER": 565,
  "TUPPER": 566,
  "FRIGO": 567,
  "FRIGOBAR": 568,
  "TUPPERS": 569,
  "REFRI": 570,
  "NEVERO": 571,
  "FROST": 572,
  "METELA": 573,
  "TAPER": 574,
  "NEVERITA": 575,
  "NEVE": 576,
  "CIERRALA": 577,
  "MININEVERA": 578,
  "HELADERITA": 579,
  "CALDERA": 580,
  "CALDERILLA": 581,
  "CALDERIN": 582,
  "NOX": 583,
  "DUVAL": 584,
  "SAUNIER": 585,
  "SMA": 586,
  "CALDEO": 587,
  "TURBINATA": 588,
  "IGNIS": 589,
  "CALDERERIA": 590,
  "CERRADURA": 591,
  "HERRADURA": 592,
  "CORREDERA": 593,
  "CERROJOS": 594,
  "BOMBIN": 595,
  "BOMBILLO": 596,
  "PICAPORTE": 597,
  "CORREDIZA": 598,
  "BUMPING": 599,
  "GANZUADO": 600,
  "GANZUA": 601,
  "ANTIGANZUA": 602,
  "CERROJAZO": 603,
  "INOXIDABLE": 604,
  "INOX": 605,
  "INOXIDABLES": 606,
  "OXIDABLE": 607,
  "MOLIENDA": 608,
  "CRIBA": 609,
  "CLINKER": 610,
  "MOLIENDAS": 611,
  "HIDROCICLON": 612,
  "MOLICIE": 613,
  "MOLINERIA": 614,
  "CRUSHING": 615,
  "REMOLIENDA": 616,
  "MOLIENTE": 617,
  "TAMIZADORA": 618,
  "CRIBAJE": 619,
  "CRIBADA": 620,
  "ACONDICIONADO": 621,
  "ACONDICIONADOS": 622,
  "CLIMATIZADA": 623,
  "ACONDICIONADOR": 624,
  "CLIMATIZADOR": 625,
  "ACONDICIONADA": 626,
  "CLIMATIZADO": 627,
  "ACONDICIONA": 628,
  "REACONDICIONADO": 629,
  "ACONDICIONO": 630,
  "MINISPLIT": 631,
  "INSONORIZADO": 632,
  "MINISPLITS": 633,
  "ACONDICIONADORA": 634,
  "ACOND": 635,
  "CALEFACCIONADO": 636,
  "CALEFACTADO": 637,
  "MULTISPLIT": 638,
  "ACONDICIONE": 639,
  "ACONDICONADO": 640,
  "CLIMATIC": 641,
  "ACONDIONADO": 642,
  "FRIGORIFICO": 643,
  "REFRIGERADOR": 644,
  "CONGELADOR": 645,
  "FRIGORIFICA": 646,
  "FRIG": 647,
  "REFRIGERE": 648,
  "FAGOR": 649,
  "FREZZER": 650,
  "FRIGORISTA": 651,
  "FREEZERS": 652,
  "ROPA": 653,
  "LENCERIA": 654,
  "ROPITA": 655,
  "CALCETERIA": 656,
  "VERRE": 657,
  "CALIENTA": 658,
  "ENFRIA": 659,
  "CONGELA": 660,
  "CALIENTAN": 661,
  "CALENTITA": 662,
  "ESTROPEA": 663,
  "CALE": 664,
  "REFRIGERA": 665,
  "GRASIENTA": 666,
  "LUBRICA": 667,
  "EVAPORAN": 668,
  "CALENTARA": 669,
  "ABRASA": 670,
  "CALIENTITA": 671,
  "VAPORIZA": 672,
  "CALENTURIENTA": 673,
  "RECALIENTA": 674,
  "PRECALIENTA": 675,
  "CALENTORRA": 676,
  "CALEN": 677,
  "ATEMPERA": 678,
  "RELAME": 679,
  "CALENTON": 680,
  "CALENTONA": 681,
  "RETORTA": 682,
  "SOBRECALIENTA": 683,
  "ATEMPERE": 684,
  "EVAPORARA": 685,
  "PAVITA": 686,
  "ENGRASAN": 687,
  "RECALIENTAN": 688,
  "MUFLA": 689,
  "CALIE": 690,
  "CALIENT": 691,
  "CALENTORRO": 692,
  "BANERA": 693,
  "TINA": 694,
  "RETRETE": 695,
  "BIDE": 696,
  "BANE": 697,
  "BIDES": 698,
  "BANERITA": 699,
  "BANERO": 700,
  "IMPERMEABLE": 701,
  "TRANSPIRABLE": 702,
  "AISLANTE": 703,
  "ANTIDESLIZANTE": 704,
  "DESECHABLE": 705,
  "LAVABLE": 706,
  "SUMERGIBLE": 707,
  "REFLECTANTE": 708,
  "PERMEABLE": 709,
  "INFLABLE": 710,
  "REMOVIBLE": 711,
  "RESPIRABLE": 712,
  "ENROLLABLE": 713,
  "ANTIDERRAPANTE": 714,
  "HIDROFUGO": 715,
  "EMPOTRABLE": 716,
  "DESENFUNDABLE": 717,
  "IGNIFUGA": 718,
  "AMOVIBLE": 719,
  "SEMIPERMEABLE": 720,
  "CORTAVIENTO": 721,
  "CICLABLE": 722,
  "INDEFORMABLE": 723,
  "TRANSPIRE": 724,
  "ANTIRREFLECTANTE": 725,
  "HIDROFUGA": 726,
  "INSUMERGIBLE": 727,
  "HIDROFUGOS": 728,
  "ANTIDERRAME": 729,
  "TERMOCONTRAIBLE": 730,
  "INASTILLABLE": 731,
  "TERMOENCOGIBLE": 732,
  "TRASPIRABLE": 733,
  "AUTOLIMPIABLE": 734,
  "TRANSPIREN": 735,
  "INHALLABLE": 736,
  "ALOGO": 737,
  "XJK": 738,
  "BANO": 739,
  "LAVABO": 740,
  "BANITO": 741,
  "BAN": 742,
  "EQUIPADA": 743,
  "COMPUTADORA": 744,
  "COMPU": 745,
  "SUPERCOMPUTADORA": 746,
  "COMPUTADA": 747,
  "MICROCOMPUTADORA": 748,
  "MINICOMPUTADORA": 749,
  "COMPUTADORIZADA": 750,
  "HABITACION": 751,
  "DESPENSA": 752,
  "ENTRESUELO": 753,
  "COHABITACION": 754,
  "LETRINA": 755,
  "ICINA": 756,
  "HACINA": 757,
  "CAMADERIA": 758,
  "TERRAMICINA": 759,
  "HIDROMASAJE": 760,
  "HIDROMASAJES": 761,
  "PISCINA": 762,
  "ALBERCA": 763,
  "PILETA": 764,
  "PISCIS": 765,
  "CHAPOTEADERO": 766,
  "PISCI": 767,
  "PISICINA": 768,
  "PISCINITA": 769,
  "PISCINAZO": 770,
  "SOLARIUMS": 771,
  "ADIPISCING": 772,
  "PISC": 773,
  "CHAPOTEA": 774,
  "PISCINERO": 775,
  "PISCINE": 776,
  "CARCASA": 777,
  "RANURA": 778,
  "CARCASAS": 779,
  "FLEX": 780,
  "PLETINA": 781,
  "CARCA": 782,
  "CARCAZA": 783,
  "TUBELESS": 784,
  "UNIBODY": 785,
  "CASETERA": 786,
  "ARMAZON": 787,
  "TITANITA": 788,
  "TERMORRETRACTIL": 789,
  "CARCAMAL": 790,
  "MICASA": 791,
  "SUCIEDAD": 792,
  "SARRO": 793,
  "MUGRE": 794,
  "CORROIDA": 795,
  "LIMPIDEZ": 796,
  "VENTILACION": 797,
  "AIREACION": 798,
  "HIPERVENTILACION": 799,
  "VENTILATORIO": 800,
  "VENTILATORIA": 801,
  "VENTILEN": 802,
  "HIPOVENTILACION": 803,
  "VENTILATORIOS": 804,
  "CLIMATIZACION": 805,
  "INSONORIZACION": 806,
  "CLIMATIZAR": 807,
  "HUMIDIFICACION": 808,
  "DESHUMIDIFICACION": 809,
  "CLIMATICA": 810,
  "CLIMATERIA": 811,
  "INSTALACION": 812,
  "DEPURADORA": 813,
  "REINSTALACION": 814,
  "DESINSTALACION": 815,
  "INCINERADORA": 816,
  "PREINSTALACION": 817,
  "INSTALACIN": 818,
  "INSTALACI": 819,
  "VIDEOINSTALACION": 820,
  "INSTALACIONES": 821,
  "INTALACION": 822,
  "INSTALCION": 823,
  "MULTIESTACION": 824,
  "TRITURACION": 825,
  "CRIBADO": 826,
  "TRITURACIONES": 827,
  "TUBERIA": 828,
  "MANGUERA": 829,
  "CANERIA": 830,
  "TACANERIA": 831,
  "TUBER": 832,
  "TUBEY": 833,
  "PANERIA": 834,
  "TOALLAS": 835,
  "TOALLITAS": 836,
  "SERVILLETAS": 837,
  "PELUSAS": 838,
  "ALBORNOCES": 839,
  "LAVES": 840,
  "BAYETAS": 841,
  "FREGONAS": 842,
  "MOPAS": 843,
  "JABONERAS": 844,
  "LAVALAS": 845,
  "AFEITAS": 846,
  "SECALAS": 847,
  "ENJABONAS": 848,
  "MASCARILLA": 849,
  "ESPONJA": 850,
  "VASELINA": 851,
  "BARRITA": 852,
  "MOSQUETA": 853,
  "PREBASE": 854,
  "CASCARILLA": 855,
  "CARILLA": 856,
  "EXFOLIA": 857,
  "ESPONJITA": 858,
  "AMPOLLETA": 859,
  "DESMAQUILLA": 860,
  "MASCA": 861,
  "APLICALA": 862,
  "BLANQUEADORA": 863,
  "POTINGUE": 864,
  "BALSAMO": 865,
  "ALISADORA": 866,
  "ALISADA": 867,
  "EXFOLIAN": 868,
  "CARILLO": 869,
  "CASCARITA": 870,
  "CREOLINA": 871,
  "MASCARITA": 872,
  "EXFOLIADA": 873,
  "DESMAQUILLADA": 874,
  "EXFOLIACION": 875,
  "ESPONJILLA": 876,
  "DESCASCARILLA": 877,
  "APLIQUELA": 878,
  "PEDICULICIDA": 879,
  "QUIMIQUILLA": 880,
  "PIODERMA": 881,
  "LIENDRERA": 882,
  "EXFOLIARTE": 883,
  "EXFOLIO": 884,
  "ASCARIS": 885,
  "LOQUILLA": 886,
  "BIODERMA": 887,
  "DESMAQUILLADORA": 888,
  "POTINGUIL": 889,
  "CEPILLO": 890,
  "LIMPIADOR": 891,
  "CEPILLADO": 892,
  "CEPILLOS": 893,
  "PEINE": 894,
  "CEPILLAR": 895,
  "BLANQUEADOR": 896,
  "PLUMERO": 897,
  "ESTROPAJO": 898,
  "FROTE": 899,
  "RASCADOR": 900,
  "MOPA": 901,
  "CEPILLA": 902,
  "PELADOR": 903,
  "BASTONCILLO": 904,
  "CHUPON": 905,
  "MOQUILLO": 906,
  "RASPADOR": 907,
  "CEPILLARTE": 908,
  "CEPILLADA": 909,
  "RASCO": 910,
  "CEPILLAN": 911,
  "CEPILLE": 912,
  "TRAPEADOR": 913,
  "CEPILLAS": 914,
  "CEPILLITO": 915,
  "TONILLO": 916,
  "CACILLO": 917,
  "CEPILLES": 918,
  "DEPILADOR": 919,
  "CORTAPELO": 920,
  "ESCOBILLON": 921,
  "MOP": 922,
  "CEPILLEN": 923,
  "CEPILLADORA": 924,
  "ESCOBILLERO": 925,
  "ELECTRICIDAD": 926,
  "HIDROELECTRICIDAD": 927,
  "PIEZOELECTRICIDAD": 928,
  "ELECTRET": 929,
  "BIOELECTRICIDAD": 930,
  "TERMOELECTRICIDAD": 931,
  "CABLE": 932,
  "MONOMODO": 933,
  "REMOLCABLE": 934,
  "TELECABLE": 935,
  "CABLECITO": 936,
  "CABLEGRAMA": 937,
  "CABLERA": 938,
  "CABLEMODEM": 939,
  "COAXIL": 940,
  "CABLEVISION": 941,
  "TOALLA": 942,
  "BORDA": 943,
  "SERVILLETA": 944,
  "PELUSA": 945,
  "FREGONA": 946,
  "TOALLITA": 947,
  "KLEENEX": 948,
  "SECALA": 949,
  "TOALLON": 950,
  "PONTELA": 951,
  "ELECTRICA": 952,
  "HIDROELECTRICA": 953,
  "TERMOELECTRICA": 954,
  "TRIFASICA": 955,
  "ELECTRIFICADA": 956,
  "DIELECTRICA": 957,
  "CTRICA": 958,
  "ELECTROMOTRIZ": 959,
  "FOTOELECTRICA": 960,
  "RADIOELECTRICA": 961,
  "ELECTRICAL": 962,
  "BIOELECTRICA": 963,
  "ELECTROCUTADA": 964,
  "ELECTROCUTA": 965,
  "NUCLEOELECTRICA": 966,
  "PIEZOELECTRICA": 967,
  "ELECTROCUTO": 968,
  "ELCTRICA": 969,
  "ELECTRIFICA": 970,
  "ELECTRICITY": 971,
  "ELECTRA": 972,
  "ELECTRIZA": 973,
  "ELECTRIFICADORA": 974,
  "COCCION": 975,
  "EBULLICION": 976,
  "FRITURA": 977,
  "TUESTA": 978,
  "OSTION": 979,
  "CENTRIFUGADA": 980,
  "COMPACTA": 981,
  "ENVOLVENTE": 982,
  "MANEJABLE": 983,
  "COMPACTAS": 984,
  "VENTOSA": 985,
  "VOLUMINOSA": 986,
  "COMPACTADO": 987,
  "COMPACTAR": 988,
  "COMPACTADA": 989,
  "APILABLE": 990,
  "AUTOPROPULSADA": 991,
  "NIVELADORA": 992,
  "TRANSPALETA": 993,
  "PLEGADORA": 994,
  "COMPACTADORA": 995,
  "CONDENSADORA": 996,
  "COMPACTAN": 997,
  "MULTIFLORA": 998,
  "COMPACTE": 999,
  "RENDIDORA": 1000
}